hybridtffs/__init__.py
hybridtffs/app.py
hybridtffs-0.1.7.dist-info/LICENSE
hybridtffs-0.1.7.dist-info/METADATA
hybridtffs-0.1.7.dist-info/WHEEL
hybridtffs-0.1.7.dist-info/top_level.txt
hybridtffs-0.1.7.dist-info/RECORD
