Metadata-Version: 2.1
Name: hybridtffs
Version: 0.1.7
Summary: Mo ta ngan
Home-page: https://github.com/VuKieuAnh/hybrid-tffs.git
Author: kieuanh
Author-email: vukieuanh.hnue@gmail.com
Classifier: Programming Language :: Python :: 3
Classifier: License :: OSI Approved :: MIT License
Classifier: Operating System :: OS Independent
Requires-Python: >=3.6
License-File: LICENSE
Requires-Dist: numpy >=1.21.0
Requires-Dist: pandas >=1.3.0
Requires-Dist: scikit-learn >=1.0.2
Requires-Dist: mlxtend >=0.19.0
Requires-Dist: tffs
